miso/__init__.py
miso/__main__.py
miso/data/__init__.py
miso/data/dataset.py
miso/data/download.py
miso/data/filenames_dataset.py
miso/data/image_dataset.py
miso/data/image_loader.py
miso/data/image_utils.py
miso/data/tf_generator.py
miso/data/training_dataset.py
miso/data/utils.py
miso/deploy/__init__.py
miso/deploy/inference.py
miso/deploy/model_info.py
miso/deploy/saving.py
miso/deploy/server.py
miso/layers/__init__.py
miso/layers/_common_blocks.py
miso/layers/asoftmax.py
miso/layers/batch_instance_normalisation.py
miso/layers/cyclic.py
miso/layers/group_normalisation.py
miso/layers/msoftmax.py
miso/models/__init__.py
miso/models/base_cyclic.py
miso/models/factory.py
miso/models/model_zoo.py
miso/models/resnet_cyclic.py
miso/models/transfer_learning.py
miso/stats/__init__.py
miso/stats/accuracy.py
miso/stats/confusion_matrix.py
miso/stats/embedding.py
miso/stats/mislabelling.py
miso/stats/most_representative.py
miso/stats/projections.py
miso/stats/training.py
miso/training/__init__.py
miso/training/adaptive_learning_rate.py
miso/training/parameters.py
miso/training/tf_augmentation.py
miso/training/trainer.py
miso/training/training_result.py
miso/utils/__init__.py
miso/utils/flowcam.py
miso/utils/lock.py
miso/utils/misc.py
miso/utils/rolling_buffer.py
miso/utils/singleton.py
miso/utils/wave.py
miso2-3.0.7.dist-info/LICENCE.txt
miso2-3.0.7.dist-info/METADATA
miso2-3.0.7.dist-info/WHEEL
miso2-3.0.7.dist-info/top_level.txt
miso2-3.0.7.dist-info/RECORD
