Metadata-Version: 2.1
Name: miso2
Version: 3.0.7
Summary: Python scripts for training CNNs for particle classification
Home-page: https://github.com/microfossil/particle-classification
Author: Ross Marchant
Author-email: ross.g.marchant@gmail.com
License: MIT
Project-URL: Source, https://github.com/microfossil/particle-classification
Project-URL: Paper, https://jm.copernicus.org/articles/39/183/2020/
Keywords: microfossil,cnn
Classifier: Development Status :: 5 - Production/Stable
Classifier: Intended Audience :: Science/Research
Requires-Python: >=3.6
License-File: LICENCE.txt
Requires-Dist: image-classifiers >=1.0.0
Requires-Dist: lxml
Requires-Dist: matplotlib
Requires-Dist: numpy
Requires-Dist: pandas
Requires-Dist: Pillow
Requires-Dist: imagecodecs
Requires-Dist: scikit-image
Requires-Dist: scikit-learn
Requires-Dist: scipy
Requires-Dist: segmentation-models
Requires-Dist: dill
Requires-Dist: flask ==1.1.2
Requires-Dist: itsdangerous ==1.1.0
Requires-Dist: tqdm
Requires-Dist: openpyxl
Requires-Dist: imblearn
Requires-Dist: tf2onnx
Requires-Dist: protobuf ==3.20.3
Requires-Dist: cleanlab
Requires-Dist: packaging
Requires-Dist: tensorflow-addons
